ai_pr_review/__init__.py
ai_pr_review/config.py
ai_pr_review/main.py
ai_pr_review/clients/__init__.py
ai_pr_review/clients/azure.py
ai_pr_review/clients/base.py
ai_pr_review/clients/github.py
ai_pr_review/clients/gitlab.py
ai_pr_review/utils/__init__.py
ai_pr_review/utils/gemini_analyze.py
ai_pr_reviewer-0.0.13.dist-info/licenses/LICENSE
ai_pr_reviewer-0.0.13.dist-info/METADATA
ai_pr_reviewer-0.0.13.dist-info/WHEEL
ai_pr_reviewer-0.0.13.dist-info/entry_points.txt
ai_pr_reviewer-0.0.13.dist-info/top_level.txt
ai_pr_reviewer-0.0.13.dist-info/RECORD
