Metadata-Version: 2.4
Name: ai-pr-reviewer
Version: 0.0.13
Summary: A cross-platform code review tool using Gemini AI for GitHub, GitLab, and Azure DevOps.
Author-email: Hoang Nguyen <hoanghuynguyen0403@gmail.com>
License-Expression: MIT
Project-URL: Homepage, https://github.com/HoangNguyen0403
Project-URL: Repository, https://github.com/HoangNguyen0403/ai_code_reviewer
Project-URL: Issues, https://github.com/HoangNguyen0403/ai_code_reviewer/issues
Requires-Python: >=3.10
License-File: LICENSE
Requires-Dist: google-generativeai
Requires-Dist: aiohttp
Requires-Dist: asyncio
Requires-Dist: unidiff
Requires-Dist: aiofiles
Requires-Dist: google-ai-generativelanguage==0.6.10
Requires-Dist: github3.py==1.3.0
Requires-Dist: requests
Dynamic: license-file
